{"files":{"packages/config/dist/index.js":{"size":33,"mtime_nanos":1776036261758614831,"mode":420,"is_dir":false},"packages/config/dist/index.d.cts":{"size":13,"mtime_nanos":1776036262220499627,"mode":420,"is_dir":false},"packages/config/dist/index.cjs":{"size":431,"mtime_nanos":1776036261758840372,"mode":420,"is_dir":false},"packages/config/dist/index.cjs.map":{"size":158,"mtime_nanos":1776036261759935494,"mode":420,"is_dir":false},"packages/config/.turbo/turbo-build.log":{"size":892,"mtime_nanos":1776036262262153507,"mode":420,"is_dir":false},"packages/config/dist":{"size":0,"mtime_nanos":0,"mode":0,"is_dir":true},"packages/config/dist/index.js.map":{"size":71,"mtime_nanos":1776036261759288287,"mode":420,"is_dir":false},"packages/config/dist/index.d.ts":{"size":13,"mtime_nanos":1776036262220538710,"mode":420,"is_dir":false}},"order":["packages/config/.turbo/turbo-build.log","packages/config/dist","packages/config/dist/index.cjs","packages/config/dist/index.cjs.map","packages/config/dist/index.d.cts","packages/config/dist/index.d.ts","packages/config/dist/index.js","packages/config/dist/index.js.map"]}